{
  "song_name": "I'LL BE HOME FOR CHRISTMAS",
  "singer": "KOKIA",
  "lyrics": "I am dreamin' tonight of a place I loveEven more than I usually doAnd although I know it's a long road backI promise youI'll be home for ChristmasYou can count on mePlease have snow and mistletoeAnd presents under the treeChristmas Eve will find meWhere the love light gleamsI'll be home for ChristmasIf only in my dreamsChristmas Eve will find meWhere the love light gleamsI'll be home for ChristmasIf only in my dreamsIf only in my dreams",
  "translated_lyrics": "I am dreamin ' tonight of a place I love/loveanin than I'm on-depart I know I'm a long road backI promise youI'll be home for ChristmasYou, count on meer, snow and mistletoeAnd The treeChristmas Eve will find meWhere the love, home for Christmastime only in my dreamsChristmas Eve gleamsI'll be home for the love home for the love. ChristmasIf only in my dreamsIf only in my skyscopy",
  "tone_name": "Joy"
}